k_vpn/__init__.py
k_vpn/main.py
k_vpn-1.0.0.dist-info/WHEEL
k_vpn-1.0.0.dist-info/entry_points.txt
k_vpn-1.0.0.dist-info/METADATA
k_vpn-1.0.0.dist-info/RECORD
