Metadata-Version: 2.3
Name: k-vpn
Version: 1.0.0
Summary: Automated CLI tool to fetch and connect to global VPN Gate servers securely.
Author: KpihX
License: MIT
Requires-Dist: typer>=0.9.0
Requires-Dist: rich>=13.0.0
Requires-Dist: requests>=2.0.0
Requires-Python: >=3.8
